{
  "_class": "text",
  "attributedString": {
    "_class": "attributedString",
    "attributes": [
      {
        "_class": "stringAttribute",
        "attributes": {
          "MSAttributedStringColorAttribute": {
            "_class": "color",
            "alpha": 1,
            "blue": 0.4392156863,
            "green": 0.3450980392,
            "red": 0.2666666667
          },
          "MSAttributedStringFontAttribute": {
            "_class": "fontDescriptor",
            "attributes": {
              "name": "SuisseIntl-SemiBold",
              "size": 14
            }
          },
          "paragraphStyle": {
            "_class": "paragraphStyle",
            "allowsDefaultTighteningForTruncation": 0,
            "maximumLineHeight": 18,
            "minimumLineHeight": 18
          }
        },
        "length": 20,
        "location": 0
      }
    ],
    "string": "Trailing - 12 months"
  },
  "automaticallyDrawOnUnderlyingPath": false,
  "booleanOperation": 0,
  "clippingMaskMode": 0,
  "do_objectID": "5C2230F2-D4D0-4082-90A1-7510ABA4818F",
  "dontSynchroniseWithSymbol": false,
  "exportOptions": {
    "_class": "exportOptions",
    "do_objectID": "C93BC2C8-5E08-4B2A-855F-F0EFEA23643E",
    "exportFormats": [
    ],
    "includedLayerIds": [
    ],
    "layerOptions": 0,
    "shouldTrim": false
  },
  "frame": {
    "_class": "rect",
    "constrainProportions": false,
    "do_objectID": "A50D2AA4-EB66-45B8-8465-7D458EFCC244",
    "height": 18,
    "width": 128,
    "x": 18,
    "y": 30
  },
  "glyphBounds": "{{0, 3}, {128, 14}}",
  "hasClippingMask": false,
  "isFixedToViewport": false,
  "isFlippedHorizontal": false,
  "isFlippedVertical": false,
  "isLocked": false,
  "isVisible": true,
  "layerListExpandedType": 0,
  "lineSpacingBehaviour": 1,
  "name": "Trailing - 12 months",
  "nameIsFixed": false,
  "resizingConstraint": 47,
  "resizingType": 0,
  "rotation": 0,
  "sharedStyleID": "ACE1BE2C-B381-4D6C-9E09-4DF230142E62",
  "shouldBreakMaskChain": false,
  "style": {
    "_class": "style",
    "do_objectID": "C77FEDA6-2547-491E-86D2-43D5AB59056A",
    "endMarkerType": 0,
    "miterLimit": 10,
    "startMarkerType": 0,
    "textStyle": {
      "_class": "textStyle",
      "do_objectID": "4A3D8535-7672-462D-B080-28956363BD5A",
      "encodedAttributes": {
        "MSAttributedStringColorAttribute": {
          "_class": "color",
          "alpha": 1,
          "blue": 0.4392156863,
          "green": 0.3450980392,
          "red": 0.2666666667
        },
        "MSAttributedStringFontAttribute": {
          "_class": "fontDescriptor",
          "attributes": {
            "name": "SuisseIntl-SemiBold",
            "size": 14
          }
        },
        "paragraphStyle": {
          "_class": "paragraphStyle",
          "allowsDefaultTighteningForTruncation": 0,
          "maximumLineHeight": 18,
          "minimumLineHeight": 18
        }
      },
      "verticalAlignment": 0
    },
    "windingRule": 1
  },
  "textBehaviour": 0
}