{
  "_class": "bitmap",
  "booleanOperation": -1,
  "clippingMask": "{{0, 0}, {1, 1}}",
  "clippingMaskMode": 0,
  "do_objectID": "9685EF11-DD4A-4C4E-BCFE-F5CA509BABF2",
  "exportOptions": {
    "_class": "exportOptions",
    "do_objectID": "48F4B1DC-247B-41CD-BCBF-AFD2C55EEAF8",
    "exportFormats": [
    ],
    "includedLayerIds": [
    ],
    "layerOptions": 0,
    "shouldTrim": false
  },
  "fillReplacesImage": false,
  "frame": {
    "_class": "rect",
    "constrainProportions": true,
    "do_objectID": "70F0D63D-2469-4126-AE40-62FF0CA2702B",
    "height": 32.22222222222222,
    "width": 39.99999999999996,
    "x": -9.411764705882343,
    "y": -5.555555555555555
  },
  "hasClippingMask": false,
  "image": {
    "_class": "MSJSONFileReference",
    "_ref": "images/ec05ffbf35a29270a4de6f3f29863fffb46ba3c5.png",
    "_ref_class": "MSImageData"
  },
  "intendedDPI": 72,
  "isFixedToViewport": false,
  "isFlippedHorizontal": false,
  "isFlippedVertical": false,
  "isLocked": false,
  "isVisible": true,
  "layerListExpandedType": 0,
  "name": "Bitmap",
  "nameIsFixed": false,
  "resizingConstraint": 63,
  "resizingType": 0,
  "rotation": 0,
  "shouldBreakMaskChain": false,
  "style": {
    "_class": "style",
    "do_objectID": "15C24594-9E63-4579-A98A-993551071F2C",
    "endMarkerType": 0,
    "miterLimit": 10,
    "startMarkerType": 0,
    "windingRule": 1
  }
}