{
  "_class": "bitmap",
  "booleanOperation": -1,
  "clippingMask": "{{0, 0}, {1, 1}}",
  "clippingMaskMode": 0,
  "do_objectID": "329756C0-78E8-4206-AE33-A7B2B0D36D7B",
  "exportOptions": {
    "_class": "exportOptions",
    "do_objectID": "4DEA5B68-79BC-4F7D-A49A-A247269A1852",
    "exportFormats": [
    ],
    "includedLayerIds": [
    ],
    "layerOptions": 0,
    "shouldTrim": false
  },
  "fillReplacesImage": false,
  "frame": {
    "_class": "rect",
    "constrainProportions": true,
    "do_objectID": "DC5375D1-BDBE-4FB3-B459-8DA9A8A143CB",
    "height": 30,
    "width": 30,
    "x": 50,
    "y": 47.00000000000006
  },
  "hasClippingMask": false,
  "image": {
    "_class": "MSJSONFileReference",
    "_ref": "images/5490c7ade4b14df316d2f3bd5646773c35e3aaed.png",
    "_ref_class": "MSImageData"
  },
  "intendedDPI": 72,
  "isFixedToViewport": false,
  "isFlippedHorizontal": false,
  "isFlippedVertical": false,
  "isLocked": false,
  "isVisible": true,
  "layerListExpandedType": 0,
  "name": "Bitmap",
  "nameIsFixed": false,
  "resizingConstraint": 63,
  "resizingType": 0,
  "rotation": -45,
  "shouldBreakMaskChain": false,
  "style": {
    "_class": "style",
    "do_objectID": "6E427465-FB27-474B-A12D-D752434776D4",
    "endMarkerType": 0,
    "miterLimit": 10,
    "startMarkerType": 0,
    "windingRule": 1
  }
}