{
  "_class": "group",
  "booleanOperation": -1,
  "clippingMaskMode": 0,
  "do_objectID": "FE87DDDE-83D5-4EAC-B908-D7E7167D48AE",
  "exportOptions": {
    "_class": "exportOptions",
    "do_objectID": "F441E24C-2A9D-4049-8AC6-0D5130888818",
    "exportFormats": [
    ],
    "includedLayerIds": [
    ],
    "layerOptions": 0,
    "shouldTrim": false
  },
  "frame": {
    "_class": "rect",
    "constrainProportions": false,
    "do_objectID": "FEE06113-B6F7-4CF6-8778-AF41138065F5",
    "height": 34,
    "width": 1346,
    "x": 0,
    "y": 0
  },
  "groupLayout": {
    "_class": "MSImmutableFreeformGroupLayout",
    "do_objectID": "C2D50E21-ADF5-4FC3-90C9-B14E8C73E650"
  },
  "hasClickThrough": false,
  "hasClippingMask": false,
  "isFixedToViewport": false,
  "isFlippedHorizontal": false,
  "isFlippedVertical": false,
  "isLocked": false,
  "isVisible": true,
  "layerListExpandedType": 0,
  "layers": [
    {
      "class": "bitmap",
      "id": "14343F51-4F3E-4A09-94CB-B6118E8C1849"
    },
    {
      "class": "text",
      "id": "FED3A75F-4D49-455F-A735-313996B48E68"
    },
    {
      "class": "group",
      "id": "D77565F3-CDF0-4C81-B458-C6A6906B2C91"
    }
  ],
  "name": "Group 2",
  "nameIsFixed": false,
  "resizingConstraint": 63,
  "resizingType": 0,
  "rotation": 0,
  "shouldBreakMaskChain": false,
  "style": {
    "_class": "style",
    "do_objectID": "95243B1F-73C0-4A69-9A40-CFA7EC0AB9AB",
    "endMarkerType": 0,
    "miterLimit": 10,
    "startMarkerType": 0,
    "windingRule": 1
  }
}